paperscraper/__init__.py
paperscraper/async_utils.py
paperscraper/impact.py
paperscraper/load_dumps.py
paperscraper/plotting.py
paperscraper/postprocessing.py
paperscraper/utils.py
paperscraper/arxiv/__init__.py
paperscraper/arxiv/arxiv.py
paperscraper/arxiv/utils.py
paperscraper/citations/__init__.py
paperscraper/citations/citations.py
paperscraper/citations/core.py
paperscraper/citations/orcid.py
paperscraper/citations/self_citations.py
paperscraper/citations/self_references.py
paperscraper/citations/utils.py
paperscraper/citations/entity/__init__.py
paperscraper/citations/entity/core.py
paperscraper/citations/entity/paper.py
paperscraper/citations/entity/researcher.py
paperscraper/citations/tests/__init__.py
paperscraper/citations/tests/test_citations.py
paperscraper/citations/tests/test_paper.py
paperscraper/citations/tests/test_self_citations.py
paperscraper/citations/tests/test_self_references.py
paperscraper/get_dumps/__init__.py
paperscraper/get_dumps/arxiv.py
paperscraper/get_dumps/biorxiv.py
paperscraper/get_dumps/chemrxiv.py
paperscraper/get_dumps/medrxiv.py
paperscraper/get_dumps/utils/__init__.py
paperscraper/get_dumps/utils/chemrxiv/__init__.py
paperscraper/get_dumps/utils/chemrxiv/chemrxiv_api.py
paperscraper/get_dumps/utils/chemrxiv/utils.py
paperscraper/pdf/__init__.py
paperscraper/pdf/fallbacks.py
paperscraper/pdf/pdf.py
paperscraper/pdf/utils.py
paperscraper/pubmed/__init__.py
paperscraper/pubmed/pubmed.py
paperscraper/pubmed/utils.py
paperscraper/pubmed/tests/__init__.py
paperscraper/pubmed/tests/test_pubmed.py
paperscraper/scholar/__init__.py
paperscraper/scholar/core.py
paperscraper/scholar/scholar.py
paperscraper/scholar/tests/__init__.py
paperscraper/scholar/tests/test_scholar.py
paperscraper/server_dumps/__init__.py
paperscraper/tests/__init__.py
paperscraper/tests/test_dump.py
paperscraper/tests/test_impactor.py
paperscraper/tests/test_pdf.py
paperscraper/xrxiv/__init__.py
paperscraper/xrxiv/xrxiv_api.py
paperscraper/xrxiv/xrxiv_query.py
paperscraper-0.3.5.dist-info/licenses/LICENSE
paperscraper-0.3.5.dist-info/METADATA
paperscraper-0.3.5.dist-info/WHEEL
paperscraper-0.3.5.dist-info/top_level.txt
paperscraper-0.3.5.dist-info/RECORD
