Metadata-Version: 2.4
Name: paperscraper
Version: 0.3.5
Summary: paperscraper: Package to scrape papers.
Author-email: Jannis Born <jannis.born@gmx.de>, Matteo Manica <drugilsberg@gmail.com>
License: MIT
Project-URL: Homepage, https://github.com/jannisborn/paperscraper
Project-URL: Documentation, https://jannisborn.github.io/paperscraper/
Project-URL: Repository, https://github.com/jannisborn/paperscraper
Keywords: Academics,Science,Publication,Search,PubMed,Arxiv,Medrxiv,Biorxiv,Chemrxiv,Google Scholar
Classifier: Development Status :: 3 - Alpha
Classifier: Intended Audience :: Developers
Classifier: Intended Audience :: Science/Research
Classifier: License :: OSI Approved :: MIT License
Classifier: Programming Language :: Python :: 3
Classifier: Programming Language :: Python :: 3.9
Classifier: Programming Language :: Python :: 3.10
Classifier: Programming Language :: Python :: 3.11
Classifier: Programming Language :: Python :: 3.12
Classifier: Programming Language :: Python :: 3.13
Classifier: Topic :: Software Development :: Libraries :: Python Modules
Requires-Python: >=3.9
License-File: LICENSE
Requires-Dist: arxiv>=1.4.7
Requires-Dist: pymed-paperscraper>=1.0.4
Requires-Dist: pandas>=1.0.4
Requires-Dist: requests>=2.32.2
Requires-Dist: tqdm>=4.51.0
Requires-Dist: scholarly>=1.0.0
Requires-Dist: seaborn>=0.11.0
Requires-Dist: matplotlib>=3.3.2
Requires-Dist: matplotlib-venn>=0.11.5
Requires-Dist: bs4>=0.0.1
Requires-Dist: impact-factor>=1.1.3
Requires-Dist: thefuzz>=0.20.0
Requires-Dist: pytest
Requires-Dist: tldextract
Requires-Dist: semanticscholar>=0.8.4
Requires-Dist: pydantic
Requires-Dist: unidecode
Requires-Dist: dotenv
Requires-Dist: boto3
Dynamic: license-file
